tensor2tensor/__init__.py
tensor2tensor/problems.py
tensor2tensor/problems_test.py
tensor2tensor/data_generators/__init__.py
tensor2tensor/data_generators/algorithmic.py
tensor2tensor/data_generators/algorithmic_math.py
tensor2tensor/data_generators/algorithmic_math_test.py
tensor2tensor/data_generators/algorithmic_test.py
tensor2tensor/data_generators/all_problems.py
tensor2tensor/data_generators/all_problems_test.py
tensor2tensor/data_generators/audio.py
tensor2tensor/data_generators/audio_test.py
tensor2tensor/data_generators/cipher.py
tensor2tensor/data_generators/cnn_dailymail.py
tensor2tensor/data_generators/desc2code.py
tensor2tensor/data_generators/desc2code_test.py
tensor2tensor/data_generators/dna_encoder.py
tensor2tensor/data_generators/dna_encoder_test.py
tensor2tensor/data_generators/gene_expression.py
tensor2tensor/data_generators/gene_expression_test.py
tensor2tensor/data_generators/generator_utils.py
tensor2tensor/data_generators/generator_utils_test.py
tensor2tensor/data_generators/ice_parsing.py
tensor2tensor/data_generators/image.py
tensor2tensor/data_generators/image_test.py
tensor2tensor/data_generators/imdb.py
tensor2tensor/data_generators/inspect.py
tensor2tensor/data_generators/librispeech.py
tensor2tensor/data_generators/lm1b.py
tensor2tensor/data_generators/multinli.py
tensor2tensor/data_generators/problem.py
tensor2tensor/data_generators/problem_hparams.py
tensor2tensor/data_generators/ptb.py
tensor2tensor/data_generators/snli.py
tensor2tensor/data_generators/text_encoder.py
tensor2tensor/data_generators/text_encoder_build_subword.py
tensor2tensor/data_generators/text_encoder_test.py
tensor2tensor/data_generators/tokenizer.py
tensor2tensor/data_generators/tokenizer_test.py
tensor2tensor/data_generators/translate.py
tensor2tensor/data_generators/translate_encs.py
tensor2tensor/data_generators/translate_ende.py
tensor2tensor/data_generators/translate_enfr.py
tensor2tensor_dev-1.3.1.dev7.dist-info/DESCRIPTION.rst
tensor2tensor_dev-1.3.1.dev7.dist-info/METADATA
tensor2tensor_dev-1.3.1.dev7.dist-info/RECORD
tensor2tensor_dev-1.3.1.dev7.dist-info/WHEEL
tensor2tensor_dev-1.3.1.dev7.dist-info/metadata.json
tensor2tensor_dev-1.3.1.dev7.dist-info/top_level.txt
