Metadata-Version: 2.0
Name: tensor2tensor-dev
Version: 1.3.1.dev7
Summary: Tensor2Tensor
Home-page: http://github.com/tensorflow/tensor2tensor
Author: Google Inc.
Author-email: no-reply@google.com
License: Apache 2.0
Keywords: tensorflow machine learning
Platform: UNKNOWN
Classifier: Development Status :: 4 - Beta
Classifier: Intended Audience :: Developers
Classifier: Intended Audience :: Science/Research
Classifier: License :: OSI Approved :: Apache Software License
Classifier: Topic :: Scientific/Engineering :: Artificial Intelligence
Requires-Dist: bz2file
Requires-Dist: future
Requires-Dist: numpy
Requires-Dist: requests
Requires-Dist: sympy
Requires-Dist: six
Provides-Extra: tensorflow
Requires-Dist: tensorflow (>=1.4.0); extra == 'tensorflow'
Provides-Extra: tensorflow_gpu
Requires-Dist: tensorflow-gpu (>=1.4.0); extra == 'tensorflow_gpu'
Provides-Extra: tests
Requires-Dist: pytest; extra == 'tests'
Requires-Dist: h5py; extra == 'tests'
Requires-Dist: mock; extra == 'tests'
